metamart_source_metabase/__init__.py
metamart_source_metabase/adapters.py
metamart_source_metabase/api.py
metamart_source_metabase/base.py
metamart_source_metabase/loader.py
metamart_source_metabase/mock_tools.py
metamart_source_metabase/models.py
metamart_source_metabase/package_definitions.py
metamart_source_metabase/py.typed
metamart_source_metabase-0.2.6.dist-info/METADATA
metamart_source_metabase-0.2.6.dist-info/WHEEL
metamart_source_metabase-0.2.6.dist-info/RECORD
