Metadata-Version: 2.1
Name: metamart-source-metabase
Version: 0.2.6
Summary: 
Author: Elseagle
Author-email: dowolebolu@gmail.com
Requires-Python: >=3.8,<4.0
Classifier: Programming Language :: Python :: 3
Classifier: Programming Language :: Python :: 3.8
Classifier: Programming Language :: Python :: 3.9
Classifier: Programming Language :: Python :: 3.10
Classifier: Programming Language :: Python :: 3.11
Classifier: Programming Language :: Python :: 3.12
Requires-Dist: httpx[http2] (>=0.24.1,<0.25.0)
Requires-Dist: metamart-schemas (>=0.2.7-alpha3,<0.3.0)
Requires-Dist: multimethod (>=1.8,<2.0,!=1.11)
Requires-Dist: pydantic (>=1.10.9,<2.0.0)
Requires-Dist: requests (>=2.31.0,<3.0.0)
Requires-Dist: retrying (>=1.3.4,<2.0.0)
